dictipy/__init__.py
dictipy/dict_maker.py
dictipy-0.0.4.dist-info/LICENSE
dictipy-0.0.4.dist-info/METADATA
dictipy-0.0.4.dist-info/WHEEL
dictipy-0.0.4.dist-info/top_level.txt
dictipy-0.0.4.dist-info/RECORD
